gpod/__init__.py
gpod/detectors.py
gpod/markobjects.py
gpod-0.1.2.dist-info/DESCRIPTION.rst
gpod-0.1.2.dist-info/METADATA
gpod-0.1.2.dist-info/RECORD
gpod-0.1.2.dist-info/WHEEL
gpod-0.1.2.dist-info/metadata.json
gpod-0.1.2.dist-info/top_level.txt
