Metadata-Version: 2.0
Name: gpod
Version: 0.1.2
Summary: general purpose object detector
Home-page: https://github.com/EvgenyNekrasov/gpod
Author: Evgeny Nekrasov
Author-email: evgeny.nekrasov@phystech.edu
License: BSD 3-Clause License
Keywords: image recognition vision detection
Platform: UNKNOWN
Classifier: Development Status :: 4 - Beta
Classifier: Topic :: Software Development :: Libraries
Classifier: Topic :: Scientific/Engineering :: Artificial Intelligence
Classifier: Topic :: Scientific/Engineering :: Image Recognition
Classifier: License :: OSI Approved :: BSD License
Classifier: Programming Language :: Python :: 2.7
Classifier: Programming Language :: Python :: 3.5
Requires-Dist: numpy
Requires-Dist: scipy
